LightBridge/Android.py
LightBridge/Linux.py
LightBridge/Mac.py
LightBridge/Windows.py
LightBridge/__init__.py
LightBridge_hbisneto-1.1.dist-info/LICENSE
LightBridge_hbisneto-1.1.dist-info/METADATA
LightBridge_hbisneto-1.1.dist-info/WHEEL
LightBridge_hbisneto-1.1.dist-info/top_level.txt
LightBridge_hbisneto-1.1.dist-info/RECORD
