Metadata-Version: 2.1
Name: LightBridge-hbisneto
Version: 1.1
Summary: A PyBridge extension to manipulate FileSystem locations on any platform
Home-page: https://github.com/hbisneto/LightBridge/
Author: Heitor Bisneto
Author-email: heitor.bardemaker@live.com
Maintainer: Heitor Bisneto
Maintainer-email: heitor.bardemaker@live.com
License: MIT
Project-URL: Source, https://github.com/hbisneto/LightBridge/
Project-URL: Tracker, https://github.com/hbisneto/LightBridge/issues
Keywords: bridge,ponte,virtual
Platform: any
Classifier: Development Status :: 5 - Production/Stable
Classifier: Intended Audience :: Developers
Classifier: License :: OSI Approved :: MIT License
Classifier: Operating System :: POSIX :: Linux
Classifier: Operating System :: MacOS :: MacOS X
Classifier: Operating System :: Microsoft :: Windows
Classifier: Programming Language :: Python :: 3.9
Classifier: Programming Language :: Python :: Implementation :: PyPy
Classifier: Topic :: Software Development :: Libraries
Classifier: Topic :: Software Development :: Testing
Classifier: Topic :: Utilities
Requires-Python: >=3.9
License-File: LICENSE
